logging_colorizer.py
logging_colorizer-0.0.14.dist-info/METADATA
logging_colorizer-0.0.14.dist-info/WHEEL
logging_colorizer-0.0.14.dist-info/top_level.txt
logging_colorizer-0.0.14.dist-info/RECORD
