Metadata-Version: 2.1
Name: logging-colorizer
Version: 0.0.14
Summary: This library is based on the requests library but it colorizes the logs.
Author: Ali Kianigohar
Classifier: Programming Language :: Python :: 3
Classifier: License :: OSI Approved :: MIT License
Classifier: Operating System :: OS Independent
Requires-Python: >=3.6
Requires-Dist: requests
Requires-Dist: colorlog >=6.7.0
